synse_plugin/__init__.py
synse_plugin/synse_pb2.py
synse_plugin/synse_pb2_grpc.py
synse_plugin-0.0.3.dist-info/DESCRIPTION.rst
synse_plugin-0.0.3.dist-info/METADATA
synse_plugin-0.0.3.dist-info/RECORD
synse_plugin-0.0.3.dist-info/WHEEL
synse_plugin-0.0.3.dist-info/metadata.json
synse_plugin-0.0.3.dist-info/top_level.txt
