Metadata-Version: 2.0
Name: synse-plugin
Version: 0.0.3
Summary: Internal gRPC API for communication between plugins and Synse Server.
Home-page: https://github.com/vapor-ware/synse-server-grpc
Author: Vapor IO
Author-email: vapor@vapor.io
License: GNU General Public License v2.0
Platform: UNKNOWN
Classifier: License :: OSI Approved :: GNU General Public License v2 (GPLv2)
Classifier: Programming Language :: Python
Classifier: Programming Language :: Python :: 3
Classifier: Programming Language :: Python :: 3.6
Requires-Dist: grpcio (>=1.8.6)
